[
  {
    "step": 0,
    "layer": 7,
    "phi": 0.8653746843338013,
    "gamma": 0.08,
    "energy": 1.0,
    "rba_active": false,
    "hub": 11,
    "routing": "BACK-2"
  },
  {
    "step": 1,
    "layer": 8,
    "phi": 0.9677574634552002,
    "gamma": 0.08,
    "energy": 1.0,
    "rba_active": false,
    "hub": 11,
    "routing": "BACK-1"
  },
  {
    "step": 2,
    "layer": 8,
    "phi": 0.9262925386428833,
    "gamma": 0.08,
    "energy": 1.0,
    "rba_active": false,
    "hub": 9,
    "routing": "BACK-1"
  },
  {
    "step": 3,
    "layer": 8,
    "phi": 0.9484066963195801,
    "gamma": 0.08,
    "energy": 1.0,
    "rba_active": false,
    "hub": 9,
    "routing": "NEXT"
  },
  {
    "step": 4,
    "layer": 9,
    "phi": 0.9272797703742981,
    "gamma": 0.08,
    "energy": 1.0,
    "rba_active": false,
    "hub": 11,
    "routing": "BACK-2"
  },
  {
    "step": 5,
    "layer": 8,
    "phi": 0.9914560317993164,
    "gamma": 0.08,
    "energy": 1.0,
    "rba_active": true,
    "hub": 11,
    "routing": "SKIP-1"
  },
  {
    "step": 6,
    "layer": 10,
    "phi": 0.926587700843811,
    "gamma": 0.08,
    "energy": 1.0,
    "rba_active": true,
    "hub": 9,
    "routing": "BACK-2"
  },
  {
    "step": 7,
    "layer": 8,
    "phi": 0.9817577600479126,
    "gamma": 0.08,
    "energy": 1.0,
    "rba_active": true,
    "hub": 9,
    "routing": "SKIP-1"
  },
  {
    "step": 8,
    "layer": 10,
    "phi": 0.9715178608894348,
    "gamma": 0.08,
    "energy": 1.0,
    "rba_active": true,
    "hub": 11,
    "routing": "NEXT"
  },
  {
    "step": 9,
    "layer": 11,
    "phi": 0.7442168593406677,
    "gamma": 0.08,
    "energy": 1.0,
    "rba_active": true,
    "hub": 11,
    "routing": "BACK-2"
  },
  {
    "step": 10,
    "layer": 9,
    "phi": 0.9809907674789429,
    "gamma": 0.08,
    "energy": 1.0,
    "rba_active": true,
    "hub": 9,
    "routing": "NEXT"
  },
  {
    "step": 11,
    "layer": 10,
    "phi": 0.9773752093315125,
    "gamma": 0.08,
    "energy": 1.0,
    "rba_active": true,
    "hub": 9,
    "routing": "NEXT"
  },
  {
    "step": 12,
    "layer": 11,
    "phi": 0.8764603734016418,
    "gamma": 0.08,
    "energy": 1.0,
    "rba_active": true,
    "hub": 11,
    "routing": "BACK-2"
  },
  {
    "step": 13,
    "layer": 9,
    "phi": 0.9933456778526306,
    "gamma": 0.08,
    "energy": 1.0,
    "rba_active": true,
    "hub": 11,
    "routing": "SKIP-1"
  },
  {
    "step": 14,
    "layer": 11,
    "phi": 0.9514541625976562,
    "gamma": 0.08,
    "energy": 1.0,
    "rba_active": true,
    "hub": 9,
    "routing": "NEXT"
  },
  {
    "step": 15,
    "layer": 12,
    "phi": 0.9627925753593445,
    "gamma": 0.08,
    "energy": 1.0,
    "rba_active": true,
    "hub": 9,
    "routing": "BACK-1"
  },
  {
    "step": 16,
    "layer": 11,
    "phi": 0.9779426455497742,
    "gamma": 0.08,
    "energy": 1.0,
    "rba_active": true,
    "hub": 11,
    "routing": "SKIP-1"
  },
  {
    "step": 17,
    "layer": 13,
    "phi": 0.9512085318565369,
    "gamma": 0.08,
    "energy": 1.0,
    "rba_active": true,
    "hub": 11,
    "routing": "BACK-1"
  },
  {
    "step": 18,
    "layer": 12,
    "phi": 0.9720833897590637,
    "gamma": 0.08,
    "energy": 1.0,
    "rba_active": true,
    "hub": 9,
    "routing": "NEXT"
  },
  {
    "step": 19,
    "layer": 13,
    "phi": 0.9693464636802673,
    "gamma": 0.08,
    "energy": 1.0,
    "rba_active": true,
    "hub": 9,
    "routing": "NEXT"
  }
]