[
  {
    "step": 0,
    "layer": 7,
    "phi": 0.29554271697998047,
    "gamma": 0.08,
    "energy": 1.0,
    "rba_active": false,
    "hub": 11,
    "routing": "BACK-2"
  },
  {
    "step": 1,
    "layer": 8,
    "phi": 0.8925082683563232,
    "gamma": 0.08,
    "energy": 1.0,
    "rba_active": false,
    "hub": 11,
    "routing": "BACK-2"
  },
  {
    "step": 2,
    "layer": 8,
    "phi": 0.9721444845199585,
    "gamma": 0.08,
    "energy": 1.0,
    "rba_active": false,
    "hub": 9,
    "routing": "NEXT"
  },
  {
    "step": 3,
    "layer": 9,
    "phi": 0.9718894958496094,
    "gamma": 0.08,
    "energy": 1.0,
    "rba_active": false,
    "hub": 9,
    "routing": "NEXT"
  },
  {
    "step": 4,
    "layer": 10,
    "phi": 0.9506295323371887,
    "gamma": 0.08,
    "energy": 1.0,
    "rba_active": false,
    "hub": 11,
    "routing": "BACK-1"
  },
  {
    "step": 5,
    "layer": 9,
    "phi": 0.9889752268791199,
    "gamma": 0.08,
    "energy": 1.0,
    "rba_active": true,
    "hub": 11,
    "routing": "NEXT"
  },
  {
    "step": 6,
    "layer": 10,
    "phi": 0.9837178587913513,
    "gamma": 0.08,
    "energy": 1.0,
    "rba_active": true,
    "hub": 9,
    "routing": "NEXT"
  },
  {
    "step": 7,
    "layer": 11,
    "phi": 0.7396088242530823,
    "gamma": 0.08,
    "energy": 1.0,
    "rba_active": true,
    "hub": 9,
    "routing": "BACK-2"
  },
  {
    "step": 8,
    "layer": 9,
    "phi": 0.969379186630249,
    "gamma": 0.08,
    "energy": 1.0,
    "rba_active": true,
    "hub": 11,
    "routing": "NEXT"
  },
  {
    "step": 9,
    "layer": 10,
    "phi": 0.9745229482650757,
    "gamma": 0.08,
    "energy": 1.0,
    "rba_active": true,
    "hub": 11,
    "routing": "NEXT"
  },
  {
    "step": 10,
    "layer": 11,
    "phi": 0.8554385304450989,
    "gamma": 0.08,
    "energy": 1.0,
    "rba_active": true,
    "hub": 9,
    "routing": "BACK-2"
  },
  {
    "step": 11,
    "layer": 9,
    "phi": 0.987659752368927,
    "gamma": 0.08,
    "energy": 1.0,
    "rba_active": true,
    "hub": 9,
    "routing": "SKIP-1"
  },
  {
    "step": 12,
    "layer": 11,
    "phi": 0.9359233379364014,
    "gamma": 0.08,
    "energy": 1.0,
    "rba_active": true,
    "hub": 11,
    "routing": "BACK-1"
  },
  {
    "step": 13,
    "layer": 10,
    "phi": 0.9785897731781006,
    "gamma": 0.08,
    "energy": 1.0,
    "rba_active": true,
    "hub": 11,
    "routing": "SKIP-1"
  },
  {
    "step": 14,
    "layer": 12,
    "phi": 0.9447646737098694,
    "gamma": 0.08,
    "energy": 1.0,
    "rba_active": true,
    "hub": 9,
    "routing": "BACK-1"
  },
  {
    "step": 15,
    "layer": 11,
    "phi": 0.94509357213974,
    "gamma": 0.08,
    "energy": 1.0,
    "rba_active": true,
    "hub": 9,
    "routing": "NEXT"
  },
  {
    "step": 16,
    "layer": 12,
    "phi": 0.9409029483795166,
    "gamma": 0.08,
    "energy": 1.0,
    "rba_active": true,
    "hub": 11,
    "routing": "BACK-1"
  },
  {
    "step": 17,
    "layer": 11,
    "phi": 0.973412275314331,
    "gamma": 0.08,
    "energy": 1.0,
    "rba_active": true,
    "hub": 11,
    "routing": "SKIP-1"
  },
  {
    "step": 18,
    "layer": 13,
    "phi": 0.9173649549484253,
    "gamma": 0.08,
    "energy": 1.0,
    "rba_active": true,
    "hub": 9,
    "routing": "BACK-2"
  },
  {
    "step": 19,
    "layer": 11,
    "phi": 0.9838600158691406,
    "gamma": 0.08,
    "energy": 1.0,
    "rba_active": true,
    "hub": 9,
    "routing": "SKIP-1"
  },
  {
    "step": 20,
    "layer": 13,
    "phi": 0.9514869451522827,
    "gamma": 0.08,
    "energy": 1.0,
    "rba_active": true,
    "hub": 11,
    "routing": "BACK-1"
  },
  {
    "step": 21,
    "layer": 12,
    "phi": 0.9547109007835388,
    "gamma": 0.08,
    "energy": 1.0,
    "rba_active": true,
    "hub": 11,
    "routing": "NEXT"
  },
  {
    "step": 22,
    "layer": 13,
    "phi": 0.9729729890823364,
    "gamma": 0.08,
    "energy": 1.0,
    "rba_active": true,
    "hub": 9,
    "routing": "NEXT"
  }
]