[
  {
    "step": 0,
    "layer": 7,
    "phi": 0.3668959140777588,
    "gamma": 0.08,
    "energy": 1.0,
    "rba_active": false,
    "hub": 11,
    "routing": "BACK-2"
  },
  {
    "step": 1,
    "layer": 8,
    "phi": 0.9571004509925842,
    "gamma": 0.08,
    "energy": 1.0,
    "rba_active": false,
    "hub": 11,
    "routing": "BACK-1"
  },
  {
    "step": 2,
    "layer": 8,
    "phi": 0.9918542504310608,
    "gamma": 0.08,
    "energy": 1.0,
    "rba_active": false,
    "hub": 9,
    "routing": "SKIP-1"
  },
  {
    "step": 3,
    "layer": 10,
    "phi": 0.960735559463501,
    "gamma": 0.08,
    "energy": 1.0,
    "rba_active": false,
    "hub": 9,
    "routing": "BACK-1"
  },
  {
    "step": 4,
    "layer": 9,
    "phi": 0.9932138323783875,
    "gamma": 0.08,
    "energy": 1.0,
    "rba_active": false,
    "hub": 11,
    "routing": "NEXT"
  },
  {
    "step": 5,
    "layer": 10,
    "phi": 0.9870948195457458,
    "gamma": 0.08,
    "energy": 1.0,
    "rba_active": true,
    "hub": 11,
    "routing": "NEXT"
  },
  {
    "step": 6,
    "layer": 11,
    "phi": 0.7956516742706299,
    "gamma": 0.08,
    "energy": 1.0,
    "rba_active": true,
    "hub": 9,
    "routing": "BACK-2"
  },
  {
    "step": 7,
    "layer": 9,
    "phi": 0.9901320934295654,
    "gamma": 0.08,
    "energy": 1.0,
    "rba_active": true,
    "hub": 9,
    "routing": "NEXT"
  },
  {
    "step": 8,
    "layer": 10,
    "phi": 0.9764889478683472,
    "gamma": 0.08,
    "energy": 1.0,
    "rba_active": true,
    "hub": 11,
    "routing": "NEXT"
  },
  {
    "step": 9,
    "layer": 11,
    "phi": 0.9660601615905762,
    "gamma": 0.08,
    "energy": 1.0,
    "rba_active": true,
    "hub": 11,
    "routing": "NEXT"
  },
  {
    "step": 10,
    "layer": 12,
    "phi": 0.962262749671936,
    "gamma": 0.08,
    "energy": 1.0,
    "rba_active": true,
    "hub": 9,
    "routing": "BACK-1"
  },
  {
    "step": 11,
    "layer": 11,
    "phi": 0.9768628478050232,
    "gamma": 0.08,
    "energy": 1.0,
    "rba_active": true,
    "hub": 9,
    "routing": "NEXT"
  },
  {
    "step": 12,
    "layer": 12,
    "phi": 0.9300225377082825,
    "gamma": 0.08,
    "energy": 1.0,
    "rba_active": true,
    "hub": 11,
    "routing": "BACK-1"
  },
  {
    "step": 13,
    "layer": 11,
    "phi": 0.9711779356002808,
    "gamma": 0.08,
    "energy": 1.0,
    "rba_active": true,
    "hub": 11,
    "routing": "NEXT"
  },
  {
    "step": 14,
    "layer": 12,
    "phi": 0.9460753202438354,
    "gamma": 0.08,
    "energy": 1.0,
    "rba_active": true,
    "hub": 9,
    "routing": "NEXT"
  },
  {
    "step": 15,
    "layer": 13,
    "phi": 0.9587375521659851,
    "gamma": 0.08,
    "energy": 1.0,
    "rba_active": true,
    "hub": 9,
    "routing": "BACK-1"
  },
  {
    "step": 16,
    "layer": 12,
    "phi": 0.947998046875,
    "gamma": 0.08,
    "energy": 1.0,
    "rba_active": true,
    "hub": 11,
    "routing": "NEXT"
  },
  {
    "step": 17,
    "layer": 13,
    "phi": 0.9740793108940125,
    "gamma": 0.08,
    "energy": 1.0,
    "rba_active": true,
    "hub": 11,
    "routing": "NEXT"
  }
]