[
  {
    "step": 0,
    "layer": 7,
    "phi": 0.6120766997337341,
    "gamma": 0.08,
    "energy": 1.0,
    "rba_active": false,
    "hub": 11,
    "routing": "BACK-2"
  },
  {
    "step": 1,
    "layer": 8,
    "phi": 0.8478944301605225,
    "gamma": 0.08,
    "energy": 1.0,
    "rba_active": false,
    "hub": 11,
    "routing": "BACK-2"
  },
  {
    "step": 2,
    "layer": 8,
    "phi": 0.9605887532234192,
    "gamma": 0.08,
    "energy": 1.0,
    "rba_active": false,
    "hub": 9,
    "routing": "NEXT"
  },
  {
    "step": 3,
    "layer": 9,
    "phi": 0.9813669919967651,
    "gamma": 0.08,
    "energy": 1.0,
    "rba_active": false,
    "hub": 9,
    "routing": "NEXT"
  },
  {
    "step": 4,
    "layer": 10,
    "phi": 0.9707822203636169,
    "gamma": 0.08,
    "energy": 1.0,
    "rba_active": false,
    "hub": 11,
    "routing": "NEXT"
  },
  {
    "step": 5,
    "layer": 11,
    "phi": 0.6604673862457275,
    "gamma": 0.08,
    "energy": 1.0,
    "rba_active": true,
    "hub": 11,
    "routing": "BACK-2"
  },
  {
    "step": 6,
    "layer": 9,
    "phi": 0.9608392715454102,
    "gamma": 0.08,
    "energy": 1.0,
    "rba_active": true,
    "hub": 9,
    "routing": "NEXT"
  },
  {
    "step": 7,
    "layer": 10,
    "phi": 0.9575196504592896,
    "gamma": 0.08,
    "energy": 1.0,
    "rba_active": true,
    "hub": 9,
    "routing": "NEXT"
  },
  {
    "step": 8,
    "layer": 11,
    "phi": 0.8448270559310913,
    "gamma": 0.08,
    "energy": 1.0,
    "rba_active": true,
    "hub": 11,
    "routing": "BACK-2"
  },
  {
    "step": 9,
    "layer": 9,
    "phi": 0.988958477973938,
    "gamma": 0.08,
    "energy": 1.0,
    "rba_active": true,
    "hub": 11,
    "routing": "SKIP-1"
  },
  {
    "step": 10,
    "layer": 11,
    "phi": 0.9562667608261108,
    "gamma": 0.08,
    "energy": 1.0,
    "rba_active": true,
    "hub": 9,
    "routing": "NEXT"
  },
  {
    "step": 11,
    "layer": 12,
    "phi": 0.9560208320617676,
    "gamma": 0.08,
    "energy": 1.0,
    "rba_active": true,
    "hub": 9,
    "routing": "BACK-1"
  },
  {
    "step": 12,
    "layer": 11,
    "phi": 0.9735262393951416,
    "gamma": 0.08,
    "energy": 1.0,
    "rba_active": true,
    "hub": 11,
    "routing": "NEXT"
  },
  {
    "step": 13,
    "layer": 12,
    "phi": 0.9468459486961365,
    "gamma": 0.08,
    "energy": 1.0,
    "rba_active": true,
    "hub": 11,
    "routing": "BACK-1"
  },
  {
    "step": 14,
    "layer": 11,
    "phi": 0.9798383712768555,
    "gamma": 0.08,
    "energy": 1.0,
    "rba_active": true,
    "hub": 9,
    "routing": "SKIP-1"
  },
  {
    "step": 15,
    "layer": 13,
    "phi": 0.964853823184967,
    "gamma": 0.08,
    "energy": 1.0,
    "rba_active": true,
    "hub": 9,
    "routing": "BACK-1"
  },
  {
    "step": 16,
    "layer": 12,
    "phi": 0.9478502869606018,
    "gamma": 0.08,
    "energy": 1.0,
    "rba_active": true,
    "hub": 11,
    "routing": "NEXT"
  },
  {
    "step": 17,
    "layer": 13,
    "phi": 0.9763686656951904,
    "gamma": 0.08,
    "energy": 1.0,
    "rba_active": true,
    "hub": 11,
    "routing": "NEXT"
  }
]