[
  {
    "step": 0,
    "layer": 7,
    "phi": -0.027548328042030334,
    "gamma": 0.08,
    "energy": 1.0,
    "rba_active": false,
    "hub": 11,
    "routing": "BACK-2"
  },
  {
    "step": 1,
    "layer": 8,
    "phi": 0.9799140691757202,
    "gamma": 0.08,
    "energy": 1.0,
    "rba_active": false,
    "hub": 11,
    "routing": "NEXT"
  },
  {
    "step": 2,
    "layer": 9,
    "phi": 0.9805487990379333,
    "gamma": 0.08,
    "energy": 1.0,
    "rba_active": false,
    "hub": 9,
    "routing": "NEXT"
  },
  {
    "step": 3,
    "layer": 10,
    "phi": 0.9421780705451965,
    "gamma": 0.08,
    "energy": 1.0,
    "rba_active": false,
    "hub": 9,
    "routing": "BACK-1"
  },
  {
    "step": 4,
    "layer": 9,
    "phi": 0.9932205080986023,
    "gamma": 0.08,
    "energy": 1.0,
    "rba_active": false,
    "hub": 11,
    "routing": "SKIP-1"
  },
  {
    "step": 5,
    "layer": 11,
    "phi": 0.7658491730690002,
    "gamma": 0.08,
    "energy": 1.0,
    "rba_active": true,
    "hub": 11,
    "routing": "BACK-2"
  },
  {
    "step": 6,
    "layer": 9,
    "phi": 0.9725565910339355,
    "gamma": 0.08,
    "energy": 1.0,
    "rba_active": true,
    "hub": 9,
    "routing": "NEXT"
  },
  {
    "step": 7,
    "layer": 10,
    "phi": 0.9786982536315918,
    "gamma": 0.08,
    "energy": 1.0,
    "rba_active": true,
    "hub": 9,
    "routing": "NEXT"
  },
  {
    "step": 8,
    "layer": 11,
    "phi": 0.8972970247268677,
    "gamma": 0.08,
    "energy": 1.0,
    "rba_active": true,
    "hub": 11,
    "routing": "BACK-2"
  },
  {
    "step": 9,
    "layer": 9,
    "phi": 0.9919856786727905,
    "gamma": 0.08,
    "energy": 1.0,
    "rba_active": true,
    "hub": 11,
    "routing": "SKIP-1"
  },
  {
    "step": 10,
    "layer": 11,
    "phi": 0.9596418738365173,
    "gamma": 0.08,
    "energy": 1.0,
    "rba_active": true,
    "hub": 9,
    "routing": "NEXT"
  },
  {
    "step": 11,
    "layer": 12,
    "phi": 0.9435539245605469,
    "gamma": 0.08,
    "energy": 1.0,
    "rba_active": true,
    "hub": 9,
    "routing": "BACK-1"
  },
  {
    "step": 12,
    "layer": 11,
    "phi": 0.9653249979019165,
    "gamma": 0.08,
    "energy": 1.0,
    "rba_active": true,
    "hub": 11,
    "routing": "NEXT"
  },
  {
    "step": 13,
    "layer": 12,
    "phi": 0.9554137587547302,
    "gamma": 0.08,
    "energy": 1.0,
    "rba_active": true,
    "hub": 11,
    "routing": "NEXT"
  },
  {
    "step": 14,
    "layer": 13,
    "phi": 0.9479693174362183,
    "gamma": 0.08,
    "energy": 1.0,
    "rba_active": true,
    "hub": 9,
    "routing": "BACK-1"
  },
  {
    "step": 15,
    "layer": 12,
    "phi": 0.9724932909011841,
    "gamma": 0.08,
    "energy": 1.0,
    "rba_active": true,
    "hub": 9,
    "routing": "NEXT"
  },
  {
    "step": 16,
    "layer": 13,
    "phi": 0.973743736743927,
    "gamma": 0.08,
    "energy": 1.0,
    "rba_active": true,
    "hub": 11,
    "routing": "NEXT"
  }
]