[
  {
    "step": 0,
    "layer": 7,
    "phi": 0.3174506425857544,
    "gamma": 0.08,
    "energy": 1.0,
    "rba_active": false,
    "hub": 11,
    "routing": "BACK-2"
  },
  {
    "step": 1,
    "layer": 8,
    "phi": 0.9055807590484619,
    "gamma": 0.08,
    "energy": 1.0,
    "rba_active": false,
    "hub": 11,
    "routing": "BACK-2"
  },
  {
    "step": 2,
    "layer": 8,
    "phi": 0.9786001443862915,
    "gamma": 0.08,
    "energy": 1.0,
    "rba_active": false,
    "hub": 9,
    "routing": "NEXT"
  },
  {
    "step": 3,
    "layer": 9,
    "phi": 0.9757432341575623,
    "gamma": 0.08,
    "energy": 1.0,
    "rba_active": false,
    "hub": 9,
    "routing": "NEXT"
  },
  {
    "step": 4,
    "layer": 10,
    "phi": 0.9606860280036926,
    "gamma": 0.08,
    "energy": 1.0,
    "rba_active": false,
    "hub": 11,
    "routing": "BACK-1"
  },
  {
    "step": 5,
    "layer": 9,
    "phi": 0.9926952719688416,
    "gamma": 0.08,
    "energy": 1.0,
    "rba_active": true,
    "hub": 11,
    "routing": "SKIP-1"
  },
  {
    "step": 6,
    "layer": 11,
    "phi": 0.8568224906921387,
    "gamma": 0.08,
    "energy": 1.0,
    "rba_active": true,
    "hub": 9,
    "routing": "BACK-2"
  },
  {
    "step": 7,
    "layer": 9,
    "phi": 0.9941949844360352,
    "gamma": 0.08,
    "energy": 1.0,
    "rba_active": true,
    "hub": 9,
    "routing": "SKIP-1"
  },
  {
    "step": 8,
    "layer": 11,
    "phi": 0.9480081796646118,
    "gamma": 0.08,
    "energy": 1.0,
    "rba_active": true,
    "hub": 11,
    "routing": "BACK-1"
  },
  {
    "step": 9,
    "layer": 10,
    "phi": 0.9888351559638977,
    "gamma": 0.08,
    "energy": 1.0,
    "rba_active": true,
    "hub": 11,
    "routing": "NEXT"
  },
  {
    "step": 10,
    "layer": 11,
    "phi": 0.9738240242004395,
    "gamma": 0.08,
    "energy": 1.0,
    "rba_active": true,
    "hub": 9,
    "routing": "NEXT"
  },
  {
    "step": 11,
    "layer": 12,
    "phi": 0.9693172574043274,
    "gamma": 0.08,
    "energy": 1.0,
    "rba_active": true,
    "hub": 9,
    "routing": "NEXT"
  },
  {
    "step": 12,
    "layer": 13,
    "phi": 0.9338372349739075,
    "gamma": 0.08,
    "energy": 1.0,
    "rba_active": true,
    "hub": 11,
    "routing": "BACK-2"
  },
  {
    "step": 13,
    "layer": 11,
    "phi": 0.9791422486305237,
    "gamma": 0.08,
    "energy": 1.0,
    "rba_active": true,
    "hub": 11,
    "routing": "SKIP-1"
  },
  {
    "step": 14,
    "layer": 13,
    "phi": 0.9627065062522888,
    "gamma": 0.08,
    "energy": 1.0,
    "rba_active": true,
    "hub": 9,
    "routing": "NEXT"
  }
]