[
  {
    "step": 0,
    "layer": 7,
    "phi": 0.5346073508262634,
    "gamma": 0.08,
    "energy": 1.0,
    "rba_active": false,
    "hub": 11,
    "routing": "BACK-2"
  },
  {
    "step": 1,
    "layer": 8,
    "phi": 0.8406693935394287,
    "gamma": 0.08,
    "energy": 1.0,
    "rba_active": false,
    "hub": 11,
    "routing": "BACK-2"
  },
  {
    "step": 2,
    "layer": 8,
    "phi": 0.9784354567527771,
    "gamma": 0.08,
    "energy": 1.0,
    "rba_active": false,
    "hub": 9,
    "routing": "NEXT"
  },
  {
    "step": 3,
    "layer": 9,
    "phi": 0.9891777634620667,
    "gamma": 0.08,
    "energy": 1.0,
    "rba_active": false,
    "hub": 9,
    "routing": "NEXT"
  },
  {
    "step": 4,
    "layer": 10,
    "phi": 0.9759791493415833,
    "gamma": 0.08,
    "energy": 1.0,
    "rba_active": false,
    "hub": 11,
    "routing": "NEXT"
  },
  {
    "step": 5,
    "layer": 11,
    "phi": 0.6492305994033813,
    "gamma": 0.08,
    "energy": 1.0,
    "rba_active": true,
    "hub": 11,
    "routing": "BACK-2"
  },
  {
    "step": 6,
    "layer": 9,
    "phi": 0.9483932256698608,
    "gamma": 0.08,
    "energy": 1.0,
    "rba_active": true,
    "hub": 9,
    "routing": "BACK-1"
  },
  {
    "step": 7,
    "layer": 8,
    "phi": 0.9913828372955322,
    "gamma": 0.08,
    "energy": 1.0,
    "rba_active": true,
    "hub": 9,
    "routing": "SKIP-1"
  },
  {
    "step": 8,
    "layer": 10,
    "phi": 0.9761234521865845,
    "gamma": 0.08,
    "energy": 1.0,
    "rba_active": true,
    "hub": 11,
    "routing": "NEXT"
  },
  {
    "step": 9,
    "layer": 11,
    "phi": 0.8388208150863647,
    "gamma": 0.08,
    "energy": 1.0,
    "rba_active": true,
    "hub": 11,
    "routing": "BACK-2"
  },
  {
    "step": 10,
    "layer": 9,
    "phi": 0.9758995175361633,
    "gamma": 0.08,
    "energy": 1.0,
    "rba_active": true,
    "hub": 9,
    "routing": "NEXT"
  },
  {
    "step": 11,
    "layer": 10,
    "phi": 0.9835366606712341,
    "gamma": 0.08,
    "energy": 1.0,
    "rba_active": true,
    "hub": 9,
    "routing": "NEXT"
  },
  {
    "step": 12,
    "layer": 11,
    "phi": 0.9124042391777039,
    "gamma": 0.08,
    "energy": 1.0,
    "rba_active": true,
    "hub": 11,
    "routing": "BACK-1"
  },
  {
    "step": 13,
    "layer": 10,
    "phi": 0.9804458022117615,
    "gamma": 0.08,
    "energy": 1.0,
    "rba_active": true,
    "hub": 11,
    "routing": "SKIP-1"
  },
  {
    "step": 14,
    "layer": 12,
    "phi": 0.9488368630409241,
    "gamma": 0.08,
    "energy": 1.0,
    "rba_active": true,
    "hub": 9,
    "routing": "BACK-1"
  },
  {
    "step": 15,
    "layer": 11,
    "phi": 0.9682648777961731,
    "gamma": 0.08,
    "energy": 1.0,
    "rba_active": true,
    "hub": 9,
    "routing": "NEXT"
  },
  {
    "step": 16,
    "layer": 12,
    "phi": 0.9448927044868469,
    "gamma": 0.08,
    "energy": 1.0,
    "rba_active": true,
    "hub": 11,
    "routing": "BACK-1"
  },
  {
    "step": 17,
    "layer": 11,
    "phi": 0.9779085516929626,
    "gamma": 0.08,
    "energy": 1.0,
    "rba_active": true,
    "hub": 11,
    "routing": "SKIP-1"
  },
  {
    "step": 18,
    "layer": 13,
    "phi": 0.9214693307876587,
    "gamma": 0.08,
    "energy": 1.0,
    "rba_active": true,
    "hub": 9,
    "routing": "BACK-2"
  },
  {
    "step": 19,
    "layer": 11,
    "phi": 0.9687453508377075,
    "gamma": 0.08,
    "energy": 1.0,
    "rba_active": true,
    "hub": 9,
    "routing": "SKIP-1"
  },
  {
    "step": 20,
    "layer": 13,
    "phi": 0.9566144347190857,
    "gamma": 0.08,
    "energy": 1.0,
    "rba_active": true,
    "hub": 11,
    "routing": "NEXT"
  }
]